LICENSE
README.md
setup.cfg
setup.py
py_servicebus.egg-info/PKG-INFO
py_servicebus.egg-info/SOURCES.txt
py_servicebus.egg-info/dependency_links.txt
py_servicebus.egg-info/top_level.txt
servicebus/__init__.py
servicebus/command.py
servicebus/configuration.py
servicebus/event.py
servicebus/logging_service.py
servicebus/message.py
servicebus/parser.py
servicebus/receiver.py
servicebus/request.py
servicebus/sender.py
servicebus/service.py
servicebus/watcher.py
servicebus/pika/__init__.py
servicebus/pika/amqp_object.py
servicebus/pika/callback.py
servicebus/pika/channel.py
servicebus/pika/compat.py
servicebus/pika/connection.py
servicebus/pika/credentials.py
servicebus/pika/data.py
servicebus/pika/exceptions.py
servicebus/pika/frame.py
servicebus/pika/heartbeat.py
servicebus/pika/spec.py
servicebus/pika/utils.py
servicebus/pika/adapters/__init__.py
servicebus/pika/adapters/base_connection.py
servicebus/pika/adapters/blocking_connection.py
servicebus/pika/adapters/libev_connection.py
servicebus/pika/adapters/select_connection.py
servicebus/pika/adapters/tornado_connection.py
servicebus/pika/adapters/twisted_connection.py