Metadata-Version: 2.1
Name: py-servicebus
Version: 2.16
Summary: Provide a basic RPC and Message process framework based on RabbitMQ message server.
Home-page: https://github.com/blacktear23/py-servicebus
Download-URL: https://github.com/blacktear23/py-servicebus/downloads
Author: Rain Li
Author-email: blacktear23@gmail.com
Classifier: Development Status :: 5 - Production/Stable
Classifier: Intended Audience :: Developers
Classifier: Operating System :: OS Independent
Classifier: License :: OSI Approved :: BSD License
Classifier: Programming Language :: Python :: 2.7
Classifier: Programming Language :: Python :: 3
Classifier: Programming Language :: Python :: Implementation :: CPython
Classifier: Topic :: Software Development :: Libraries
License-File: LICENSE
